pylejandria/__init__.py
pylejandria/auto.py
pylejandria/constants.py
pylejandria/gui.py
pylejandria/math.py
pylejandria/module.py
pylejandria/tools.py
pylejandria/upload.py
pylejandria-0.1.33.dist-info/LICENSE
pylejandria-0.1.33.dist-info/METADATA
pylejandria-0.1.33.dist-info/WHEEL
pylejandria-0.1.33.dist-info/top_level.txt
pylejandria-0.1.33.dist-info/RECORD
